ffmpeg_black_split/__init__.py
ffmpeg_black_split/__main__.py
ffmpeg_black_split/_black_split.py
ffmpeg_black_split/_log.py
ffmpeg_black_split/py.typed
ffmpeg_black_split-0.7.0.dist-info/licenses/LICENSE.md
ffmpeg_black_split-0.7.0.dist-info/WHEEL
ffmpeg_black_split-0.7.0.dist-info/entry_points.txt
ffmpeg_black_split-0.7.0.dist-info/METADATA
ffmpeg_black_split-0.7.0.dist-info/RECORD
